modules/__init__.py
modules/cafetran_docx_handler.py
modules/config_manager.py
modules/document_analyzer.py
modules/docx_handler.py
modules/figure_context_manager.py
modules/find_replace.py
modules/mqxliff_handler.py
modules/pdf_rescue.py
modules/prompt_assistant.py
modules/prompt_library.py
modules/setup_wizard.py
modules/simple_segmenter.py
modules/tag_manager.py
modules/tmx_generator.py
modules/tracked_changes.py
modules/trados_docx_handler.py
modules/translation_memory.py
supervertaler-3.7.1.dist-info/METADATA
supervertaler-3.7.1.dist-info/WHEEL
supervertaler-3.7.1.dist-info/top_level.txt
supervertaler-3.7.1.dist-info/RECORD
