Metadata-Version: 2.4
Name: Supervertaler
Version: 3.7.1
Summary: AI-powered context-aware translation tool for professional translators
Home-page: https://github.com/michaelbeijer/Supervertaler
Author: Michael Beijer
Author-email: Michael Beijer <info@michaelbeijer.co.uk>
Maintainer-email: Michael Beijer <info@michaelbeijer.co.uk>
License: MIT
Project-URL: Homepage, https://github.com/michaelbeijer/Supervertaler
Project-URL: Repository, https://github.com/michaelbeijer/Supervertaler.git
Project-URL: Bug Tracker, https://github.com/michaelbeijer/Supervertaler/issues
Project-URL: Documentation, https://michaelbeijer.co.uk
Project-URL: Author Website, https://michaelbeijer.co.uk
Keywords: translation,CAT,AI,LLM,GPT,Claude,Gemini,translation-memory,localization
Classifier: Development Status :: 5 - Production/Stable
Classifier: Programming Language :: Python :: 3
Classifier: Programming Language :: Python :: 3.12
Classifier: License :: OSI Approved :: MIT License
Classifier: Operating System :: Microsoft :: Windows
Classifier: Intended Audience :: End Users/Desktop
Classifier: Topic :: Office/Business
Classifier: Topic :: Text Processing :: Linguistic
Requires-Python: >=3.12
Requires-Dist: python-docx>=0.8.11
Requires-Dist: openpyxl>=3.1.0
Requires-Dist: Pillow>=10.0.0
Requires-Dist: openai>=1.0.0
Requires-Dist: anthropic>=0.7.0
Requires-Dist: google-generativeai>=0.3.0
Dynamic: author
Dynamic: home-page
Dynamic: requires-python
